pyRaTS.py
pyRaTS-0.21.dist-info/METADATA
pyRaTS-0.21.dist-info/WHEEL
pyRaTS-0.21.dist-info/top_level.txt
pyRaTS-0.21.dist-info/RECORD
