Metadata-Version: 2.1
Name: pyRaTS
Version: 0.21
Summary: processing of (RAndom) TimeSeries for vibration fatigue
Home-page: https://github.com/ArvidTrapp/pyRaTS
Author: Arvid Trapp
Author-email: arvid.trapp@hm.edu
Maintainer: Arvid Trapp, Peter Wolfsteiner
Maintainer-email: arvid.trapp@hm.edu
Keywords: vibration fatigue, non-stationarity matrix, structural dynamics,Fatigue Damage Spectrum
Classifier: Programming Language :: Python :: 3
Classifier: License :: OSI Approved :: MIT License
Classifier: Operating System :: OS Independent
Requires-Python: >=3.6
